{
    "$schema": "http://json-schema.org/draft-07/schema#",
    "title": "SecondCreativeRequest",
    "type": "object",
    "properties": {
      "name": {
        "type": "string"
      },
      "discription": {
        "type": "string"
      },
      "image": {
        "type": "string"
      },
      "applicationAddress": {
        "type": "string"
      },
      "applicationId": {
        "type": "string"
      },
      "workId": {
        "type": "integer"
      },
      "signerName": {
        "type": "string"
      },
      "signerAddress": {
        "type": "string"
      },
      "purpose": {
        "type": "string"
      },
      "location": {
        "type": "string"
      },
      "startDate": {
        "type": "integer"
      },
      "endDate": {
        "type": "integer"
      },
      "value": {
        "type": "integer"
      },
      "guildLineVerId": {
        "type": "string"
      },
      "signature": {
        "type": "string"
      }
    },
    "required": ["name", "discription", "image", "applicationAddress", "applicationId", "workId", "signerName", "signerAddress", "purpose", "location", "startDate", "endDate", "value", "guildLineVerId", "signature"]
  }